remote_env/__init__.py
remote_env/client.py
remote_env/clientProc.py
remote_env/env_pb2.py
remote_env/env_pb2_grpc.py
remote_env/gymServer.py
remote_env/lqr_env.py
remote_env/run.py
remote_env/serverProc.py
remote_env/grpc_env/__init__.py
remote_env/grpc_env/envp_pb2.py
remote_env/grpc_env/envp_pb2_grpc.py
remote_env_test-0.0.3.data/scripts/gymServer.py
remote_env_test-0.0.3.dist-info/LICENCE
remote_env_test-0.0.3.dist-info/METADATA
remote_env_test-0.0.3.dist-info/WHEEL
remote_env_test-0.0.3.dist-info/top_level.txt
remote_env_test-0.0.3.dist-info/RECORD
