Metadata-Version: 2.1
Name: remote-env-test
Version: 0.0.3
Summary: Generate protobuf files in python and C++ to be used for remote access to RL environment
Home-page: https://gitlab.sas.com/RezaNazari/rlenv_grpc.git
Author: SAS
Author-email: support@sas.com
License: Apache 2.0
Platform: UNKNOWN
Classifier: Programming Language :: Python :: 3
Classifier: Operating System :: OS Independent
Requires-Python: >=3.6
Requires-Dist: grpcio
Requires-Dist: protobuf
Requires-Dist: gym
